<?xml version="1.0" encoding="utf-8"?>
<modification>
    <name>Nico - Speed Cache</name>
    <version>1.0</version>
    <author>nicole_89</author>
    <code>nico_speed_cache</code>
    <link>http://www.nicolette.ro</link>
    <file path="system/library/customer.php">
        <operation>
            <search limit="1"><![CDATA[$this->db->query("UPDATE " . DB_PREFIX . "customer SET ip = '" . $this->db->escape($this->request->server['REMOTE_ADDR']) . "' WHERE customer_id = '" . (int)$this->customer_id . "'");]]></search>
            <add position="replace"><![CDATA[$this->db->query("UPDATE " . DB_PREFIX . "customer SET ip = '" . $this->db->escape($this->request->server['REMOTE_ADDR']) . "' WHERE customer_id = '" . (int)$this->customer_id . "'");setcookie('_npc_cust',true,0,'/');]]></add>
        </operation>
        <operation>
            <search limit="1"><![CDATA[unset($this->session->data['customer_id']);]]></search>
            <add position="replace"><![CDATA[unset($this->session->data['customer_id']);setcookie('_npc_cust','false', time() - 3600,'/');]]></add>
        </operation>
    </file>
    
    <file path="system/library/user.php">
        <operation>
            <search limit="1"><![CDATA[$this->session->data['user_id'] = $user_query->row['user_id'];]]></search>
            <add position="replace"><![CDATA[$this->session->data['user_id'] = $user_query->row['user_id'];setcookie('_npc_cust',true,0,'/');]]></add>
        </operation>
        <operation>
            <search limit="1"><![CDATA[unset($this->session->data['user_id']);]]></search>
            <add position="replace"><![CDATA[unset($this->session->data['user_id']);setcookie('_npc_cust','false', time() - 3600,'/');]]></add>
        </operation>
    </file>

    <file path="system/library/cart.php">
        <operation>
            <search limit="1"><![CDATA[$product['product_id'] = (int)$product_id;]]></search>
            <add position="replace"><![CDATA[$product['product_id'] = (int)$product_id;setcookie('_npc_cust',true,0,'/');]]></add>
        </operation>
    </file>

    <file path="catalog/controller/common/language.php">
        <operation>
            <search limit="1"><![CDATA[if (isset($this->request->post['redirect'])) {]]></search>
            <add position="replace"><![CDATA[setcookie('_npc_cust',true,0,'/');

		if (isset($this->request->post['redirect'])) { 
			setcookie('language', $this->request->post['code'] ,0,'/');]]></add>
        </operation>
    </file>


    <file path="admin/controller/catalog/product.php">
        <operation>
            <search limit="1"><![CDATA[$this->response->redirect($this->url->link('catalog/product', 'token=' . $this->session->data['token'] . $url, 'SSL'));]]></search>
            <add position="replace"><![CDATA[
						/* nico speed cache clear */
						//$files = glob(DIR_CACHE . 'nico_speed_cache_*');
						$files = glob(DIR_CACHE . '*');

						if ($files) {
							foreach ($files as $file) {
								if (file_exists($file)) {
									unlink($file);
								}
							}
						}
						
						$this->response->redirect($this->url->link('catalog/product', 'token=' . $this->session->data['token'] . $url, 'SSL'));
				]]></add>
        </operation>
    </file>

    <file path="admin/controller/catalog/category.php">
        <operation>
            <search limit="1"><![CDATA[$this->response->redirect($this->url->link('catalog/category', 'token=' . $this->session->data['token'] . $url, 'SSL'));]]></search>
            <add position="replace"><![CDATA[
						/* nico speed cache clear */
						//$files = glob(DIR_CACHE . 'nico_speed_cache_*');
						$files = glob(DIR_CACHE . '*');

						if ($files) {
							foreach ($files as $file) {
								if (file_exists($file)) {
									unlink($file);
								}
							}
						}
						
						$this->response->redirect($this->url->link('catalog/category', 'token=' . $this->session->data['token'] . $url, 'SSL'));
				]]></add>
        </operation>
    </file>

    <file path="admin/model/extension/module.php">
        <operation>
            <search limit="1"><![CDATA[public function addModule($code, $data) {]]></search>
            <add position="replace"><![CDATA[public function addModule($code, $data) {
						/* nico speed cache clear */
						//$files = glob(DIR_CACHE . 'nico_speed_cache_*');

						//clear css
						$files = glob(DIR_TEMPLATE . '/*/css/_nico*.css');

						if ($files) {
							foreach ($files as $file) {
								if (file_exists($file)) {
									unlink($file);
								}
							}
						}

						//clear js
						$files = glob(DIR_TEMPLATE . '/*/js/_nico*.js');

						if ($files) {
							foreach ($files as $file) {
								if (file_exists($file)) {
									unlink($file);
								}
							}
						}

						//clear speed cache
						$files = glob(DIR_CACHE . '*');

						if ($files) {
							foreach ($files as $file) {
								if (file_exists($file)) {
									unlink($file);
								}
							}
						}
				]]></add>
        </operation>
        <operation>
            <search limit="1"><![CDATA[public function editModule($module_id, $data) {]]></search>
            <add position="replace"><![CDATA[public function editModule($module_id, $data) {
						/* nico speed cache clear */
						//$files = glob(DIR_CACHE . 'nico_speed_cache_*');

						//clear css
						$files = glob(DIR_TEMPLATE . '/*/css/_nico*.css');

						if ($files) {
							foreach ($files as $file) {
								if (file_exists($file)) {
									unlink($file);
								}
							}
						}

						//clear js
						$files = glob(DIR_TEMPLATE . '/*/js/_nico*.js');

						if ($files) {
							foreach ($files as $file) {
								if (file_exists($file)) {
									unlink($file);
								}
							}
						}
						
						//clear speed cache
						$files = glob(DIR_CACHE . '*');

						if ($files) {
							foreach ($files as $file) {
								if (file_exists($file)) {
									unlink($file);
								}
							}
						}
				]]></add>
        </operation>
    </file>    
</modification>
